searchophile/__init__.py
searchophile/__main__.py
searchophile/search.py
searchophile-1.0.8.dist-info/LICENSE.md
searchophile-1.0.8.dist-info/METADATA
searchophile-1.0.8.dist-info/WHEEL
searchophile-1.0.8.dist-info/entry_points.txt
searchophile-1.0.8.dist-info/top_level.txt
searchophile-1.0.8.dist-info/RECORD
